LICENSE.txt
MANIFEST.in
README.rst
pyproject.toml
setup.cfg
setup.py
pyabif/__init__.py
pyabif/__main__.py
pyabif/abif.py
pyabif/tags.csv
pyabif.egg-info/PKG-INFO
pyabif.egg-info/SOURCES.txt
pyabif.egg-info/dependency_links.txt
pyabif.egg-info/entry_points.txt
pyabif.egg-info/requires.txt
pyabif.egg-info/top_level.txt
test/infiles.zip
test/outfiles.zip
test/test__main__.py
test/test_abif.py