Metadata-Version: 2.1
Name: pyabif
Version: 0.3.0
Summary: A Python ABIF reader
Home-page: https://github.com/genadijrazdorov/pyabif
Author: Genadij Razdorov
Author-email: genadijrazdorov@gmail.com
License: UNKNOWN
Project-URL: Bug Tracker, https://github.com/genadijrazdorov/pyabif/issues
Keywords: abif reader
Platform: UNKNOWN
Classifier: Development Status :: 3 - Alpha
Classifier: Programming Language :: Python :: 3
Classifier: License :: OSI Approved :: MIT License
Classifier: Operating System :: OS Independent
Classifier: Intended Audience :: Developers
Classifier: Intended Audience :: Science/Research
Classifier: Topic :: Scientific/Engineering :: Bio-Informatics
Requires-Python: <4,>=3.6
Provides-Extra: test
